multiprocess_ftp/__init__.py
multiprocess_ftp/better_queue.py
multiprocess_ftp/destinations.py
multiprocess_ftp/downloader.py
multiprocess_ftp/proxy.py
multiprocess_ftp/sources.py
multiprocess_ftp/workers.py
multiprocess_ftp-0.2.2.dist-info/WHEEL
multiprocess_ftp-0.2.2.dist-info/METADATA
multiprocess_ftp-0.2.2.dist-info/RECORD
